{
  "/my-docu-website/blog-e2a": {
    "__comp": "a6aa9e1f",
    "__context": {
      "plugin": "63e81ca5"
    },
    "sidebar": "814f3328",
    "items": [
      {
        "content": "7661071f"
      },
      {
        "content": "f4f34a3a"
      },
      {
        "content": "8717b14a"
      },
      {
        "content": "925b3f96"
      }
    ],
    "metadata": "8f865310"
  },
  "/my-docu-website/blog/archive-6e0": {
    "__comp": "9e4087bc",
    "__context": {
      "plugin": "63e81ca5"
    },
    "archive": "b5ddec46"
  },
  "/my-docu-website/blog/first-blog-post-899": {
    "__comp": "ccc49370",
    "__context": {
      "plugin": "63e81ca5"
    },
    "sidebar": "814f3328",
    "content": "e273c56f"
  },
  "/my-docu-website/blog/long-blog-post-c9d": {
    "__comp": "ccc49370",
    "__context": {
      "plugin": "63e81ca5"
    },
    "sidebar": "814f3328",
    "content": "73664a40"
  },
  "/my-docu-website/blog/mdx-blog-post-48d": {
    "__comp": "ccc49370",
    "__context": {
      "plugin": "63e81ca5"
    },
    "sidebar": "814f3328",
    "content": "59362658"
  },
  "/my-docu-website/blog/tags-119": {
    "__comp": "01a85c17",
    "__context": {
      "plugin": "63e81ca5"
    },
    "sidebar": "814f3328",
    "tags": "84386e84"
  },
  "/my-docu-website/blog/tags/docusaurus-2fa": {
    "__comp": "6875c492",
    "__context": {
      "plugin": "63e81ca5"
    },
    "sidebar": "814f3328",
    "items": [
      {
        "content": "7661071f"
      },
      {
        "content": "f4f34a3a"
      },
      {
        "content": "8717b14a"
      },
      {
        "content": "925b3f96"
      }
    ],
    "tag": "888dcee1",
    "listMetadata": "06b0fffc"
  },
  "/my-docu-website/blog/tags/facebook-48f": {
    "__comp": "6875c492",
    "__context": {
      "plugin": "63e81ca5"
    },
    "sidebar": "814f3328",
    "items": [
      {
        "content": "7661071f"
      }
    ],
    "tag": "09341459",
    "listMetadata": "bd0835b1"
  },
  "/my-docu-website/blog/tags/hello-dde": {
    "__comp": "6875c492",
    "__context": {
      "plugin": "63e81ca5"
    },
    "sidebar": "814f3328",
    "items": [
      {
        "content": "7661071f"
      },
      {
        "content": "8717b14a"
      }
    ],
    "tag": "660b25eb",
    "listMetadata": "85c201b8"
  },
  "/my-docu-website/blog/tags/hola-88c": {
    "__comp": "6875c492",
    "__context": {
      "plugin": "63e81ca5"
    },
    "sidebar": "814f3328",
    "items": [
      {
        "content": "925b3f96"
      }
    ],
    "tag": "d0bf77fa",
    "listMetadata": "5cccdb1f"
  },
  "/my-docu-website/blog/welcome-230": {
    "__comp": "ccc49370",
    "__context": {
      "plugin": "63e81ca5"
    },
    "sidebar": "814f3328",
    "content": "d9f32620"
  },
  "/my-docu-website/markdown-page-5cc": {
    "__comp": "1f391b9e",
    "__context": {
      "plugin": "74a59f17"
    },
    "content": "393be207"
  },
  "/my-docu-website/docs-8b6": {
    "__comp": "1be78505",
    "__context": {
      "plugin": "a7eaf26d"
    },
    "versionMetadata": "935f2afb"
  },
  "/my-docu-website/docs/category/tutorial---basics-4a8": {
    "__comp": "14eb3368",
    "categoryGeneratedIndex": "9c6ccbc1"
  },
  "/my-docu-website/docs/category/tutorial---extras-976": {
    "__comp": "14eb3368",
    "categoryGeneratedIndex": "672f910b"
  },
  "/my-docu-website/docs/intro-d21": {
    "__comp": "17896441",
    "content": "0e384e19"
  },
  "/my-docu-website/docs/tutorial-basics/congratulations-07a": {
    "__comp": "17896441",
    "content": "822bd8ab"
  },
  "/my-docu-website/docs/tutorial-basics/create-a-blog-post-bd5": {
    "__comp": "17896441",
    "content": "533a09ca"
  },
  "/my-docu-website/docs/tutorial-basics/create-a-document-2da": {
    "__comp": "17896441",
    "content": "1e4232ab"
  },
  "/my-docu-website/docs/tutorial-basics/create-a-page-359": {
    "__comp": "17896441",
    "content": "5c868d36"
  },
  "/my-docu-website/docs/tutorial-basics/deploy-your-site-c00": {
    "__comp": "17896441",
    "content": "f55d3e7a"
  },
  "/my-docu-website/docs/tutorial-basics/markdown-features-2a8": {
    "__comp": "17896441",
    "content": "18c41134"
  },
  "/my-docu-website/docs/tutorial-extras/manage-docs-versions-5e9": {
    "__comp": "17896441",
    "content": "dff1c289"
  },
  "/my-docu-website/docs/tutorial-extras/translate-your-site-2f6": {
    "__comp": "17896441",
    "content": "e44a2883"
  },
  "/my-docu-website/-8bd": {
    "__comp": "1df93b7f",
    "__context": {
      "plugin": "74a59f17"
    },
    "config": "5e9f5e1a"
  }
}